isoenv.py
setup.py
isoenv.egg-info/PKG-INFO
isoenv.egg-info/SOURCES.txt
isoenv.egg-info/dependency_links.txt
isoenv.egg-info/entry_points.txt
isoenv.egg-info/requires.txt
isoenv.egg-info/top_level.txt
test/test_isoenv.py