Metadata-Version: 1.0
Name: isoenv
Version: 0.1
Summary: Tools for keeping environment specific configuration in a single repository, while only deploying the configuration for a single environment
Home-page: UNKNOWN
Author: Calen Pennington
Author-email: cpennington@wgen.net
License: UNKNOWN
Platform: UNKNOWN
